divide/__init__.py
divide/divide_by_five.py
multiply/__init__.py
multiply/multiply_by_five.py
basicpkglearning-0.1.dist-info/LICENSE.txt
basicpkglearning-0.1.dist-info/METADATA
basicpkglearning-0.1.dist-info/WHEEL
basicpkglearning-0.1.dist-info/top_level.txt
basicpkglearning-0.1.dist-info/RECORD
