Metadata-Version: 2.1
Name: basicpkglearning
Version: 0.1
Summary: A simple Python package for learning
Home-page: https://gitlab.com/codasteroid/basicpkg
Author: tester
Author-email: tester@example.com
Project-URL: Bug Tracker, https://gitlab.com/codasteroid/basicpkg/-/issues
Project-URL: repository, https://gitlab.com/codasteroid/basicpkg
Classifier: Programming Language :: Python :: 3
Classifier: License :: OSI Approved :: MIT License
Classifier: Operating System :: OS Independent
Requires-Python: >=3.6
License-File: LICENSE.txt
